bencode_cpp/_bencode.cpython-38-x86_64-linux-gnu.so
bencode_cpp/ctx.h
bencode_cpp/__init__.py
bencode_cpp/bencode.cpp
bencode_cpp/encode.cpp
bencode_cpp/py.typed
bencode_cpp/decode.cpp
bencode_cpp/common.h
bencode_cpp/__init__.pyi
bencode_cpp/overflow.h
bencode_cpp-0.0.4a1.dist-info/WHEEL
bencode_cpp-0.0.4a1.dist-info/top_level.txt
bencode_cpp-0.0.4a1.dist-info/RECORD
bencode_cpp-0.0.4a1.dist-info/METADATA
